aimmspy/__init__.py
aimmspy/model/__init__.py
aimmspy/model/declaration_section.py
aimmspy/model/enums/__init__.py
aimmspy/model/enums/args_enum.py
aimmspy/model/enums/attribute_values.py
aimmspy/model/enums/data_return_types.py
aimmspy/model/enums/identifier_flags.py
aimmspy/model/enums/me_attribute_types.py
aimmspy/model/enums/me_identifier_types.py
aimmspy/model/enums/storage_types.py
aimmspy/model/identifiers/__init__.py
aimmspy/model/identifiers/constraint.py
aimmspy/model/identifiers/data_identifiers.py
aimmspy/model/identifiers/identifier.py
aimmspy/model/identifiers/index.py
aimmspy/model/identifiers/mathematical_program.py
aimmspy/model/identifiers/parameter.py
aimmspy/model/identifiers/set.py
aimmspy/model/identifiers/utils.py
aimmspy/model/identifiers/variable.py
aimmspy/model/library.py
aimmspy/model/module.py
aimmspy/model/procedure.py
aimmspy/project/__init__.py
aimmspy/project/project.py
aimmspy/utils.py
aimmspy_cpp.cp311-win_amd64.pyd
aimmspy-25.2.1.12.dist-info/METADATA
aimmspy-25.2.1.12.dist-info/WHEEL
aimmspy-25.2.1.12.dist-info/RECORD
