Metadata-Version: 2.2
Name: aimmspy
Version: 25.2.1.12
Summary: Python bindings for the AIMMS optimization platform, built with pybind11 for seamless C++ integration. Enables efficient data exchange and interaction with AIMMS projects using pandas, polars, and pyarrow. Ideal for advanced optimization workflows requiring high-performance native code.
Keywords: AIMMS,Optimization,Operations Research,Mathematical Modeling
Author: AIMMS B.V.
Maintainer: AIMMS B.V.
License: MIT
Classifier: Programming Language :: Python :: 3
Classifier: Programming Language :: C++
Classifier: License :: OSI Approved :: MIT License
Classifier: Operating System :: OS Independent
Classifier: Intended Audience :: Developers
Classifier: Topic :: Scientific/Engineering :: Mathematics
Classifier: Topic :: Software Development :: Libraries :: Python Modules
Classifier: Topic :: Software Development :: Libraries :: Application Frameworks
Requires-Python: >=3.10
Requires-Dist: pyarrow==20.0.0
Requires-Dist: pandas
Requires-Dist: polars==1.30.0
